video_play/__init__.py
video_play/admin.py
video_play/apps.py
video_play/models.py
video_play/tests.py
video_play/urls.py
video_play/util.py
video_play/version.py
video_play/views.py
video_play/migrations/0001_initial.py
video_play/migrations/0002_auto_20210103_1706.py
video_play/migrations/0003_videosplay_is_mark_file.py
video_play/migrations/0004_videosplay_vr_projection.py
video_play/migrations/0005_auto_20210612_1648.py
video_play/migrations/0006_auto_20210619_1420.py
video_play/migrations/__init__.py
video_play/static/video_play/css/tagify.css
video_play/static/video_play/js/csrftoken.js
video_play/static/video_play/js/jquery-3.4.1.min.js
video_play/static/video_play/js/tagify.min.js
video_play/static/video_play/video-js/css/my-video-js.css
video_play/static/video_play/video-js/css/video-js.min.css
video_play/static/video_play/video-js/css/videojs-seek-buttons.css
video_play/static/video_play/video-js/css/videojs-vr.css
video_play/static/video_play/video-js/css/videojs.markers.css
video_play/static/video_play/video-js/js/video.min.js
video_play/static/video_play/video-js/js/videojs-markers.min.js
video_play/static/video_play/video-js/js/videojs-offset.js
video_play/static/video_play/video-js/js/videojs-seek-buttons.min.js
video_play/static/video_play/video-js/js/videojs-vr.js
video_play/static/video_play/video-js/lang/zh-CN.js
video_play/templates/video_detail.html
django_video_play-0.1.10.dist-info/LICENSE
django_video_play-0.1.10.dist-info/METADATA
django_video_play-0.1.10.dist-info/WHEEL
django_video_play-0.1.10.dist-info/top_level.txt
django_video_play-0.1.10.dist-info/RECORD
