Metadata-Version: 2.1
Name: django-video-play
Version: 0.1.10
Summary: Django 的视频播放器程序
Home-page: https://github.com/ldsxp
Author: lds
Author-email: 85176878@qq.com
License: GNU GPL 3
Download-URL: https://pypi.org/project/django_video_play
Keywords: play,video
Platform: any
Classifier: Development Status :: 5 - Production/Stable
Classifier: Environment :: Web Environment
Classifier: Environment :: Plugins
Classifier: Framework :: Django
Classifier: Framework :: Django :: 3.2
Classifier: Intended Audience :: Developers
Classifier: License :: OSI Approved :: GNU General Public License (GPL)
Classifier: Operating System :: OS Independent
Classifier: Programming Language :: Python
Classifier: Programming Language :: Python :: 3.9
License-File: LICENSE
Requires-Dist: ilds
Requires-Dist: djlds
Requires-Dist: django
